{
    "flows": [
        {
            "start": 35,
            "end": 21,
            "ddl": 1000,
            "duration": 1,
            "period": 300,
            "reliability": 0.9999767181278575,
            "redundantPath": [
                {
                    "redundantPathReliability": 0.9999973361380708,
                    "redundantPath": [
                        {
                            "path": [
                                35,
                                8,
                                5,
                                2,
                                21
                            ],
                            "pathEdge": [
                                40,
                                26,
                                15,
                                12
                            ],
                            "weight": 4.002315165420757,
                            "reliability": 0.997688356123173
                        },
                        {
                            "path": [
                                35,
                                8,
                                5,
                                10,
                                4,
                                2,
                                21
                            ],
                            "pathEdge": [
                                40,
                                26,
                                28,
                                23,
                                14,
                                12
                            ],
                            "weight": 6.00230818985938,
                            "reliability": 0.9976952662217838
                        }
                    ],
                    "HC": 6,
                    "OF": 0,
                    "CO": 2,
                    "WT": 0.1469838572642311
                },
                {
                    "redundantPathReliability": 0.9999971931260327,
                    "redundantPath": [
                        {
                            "path": [
                                35,
                                8,
                                5,
                                2,
                                21
                            ],
                            "pathEdge": [
                                40,
                                26,
                                15,
                                12
                            ],
                            "weight": 4.002315165420757,
                            "reliability": 0.997688356123173
                        },
                        {
                            "path": [
                                35,
                                8,
                                10,
                                4,
                                2,
                                21
                            ],
                            "pathEdge": [
                                40,
                                42,
                                23,
                                14,
                                12
                            ],
                            "weight": 5.002432273269067,
                            "reliability": 0.9975715343290366
                        }
                    ],
                    "HC": 5,
                    "OF": 0,
                    "CO": 2,
                    "WT": 0.13763806287170774
                },
                {
                    "redundantPathReliability": 0.999996849524188,
                    "redundantPath": [
                        {
                            "path": [
                                35,
                                8,
                                5,
                                2,
                                21
                            ],
                            "pathEdge": [
                                40,
                                26,
                                15,
                                12
                            ],
                            "weight": 4.002315165420757,
                            "reliability": 0.997688356123173
                        },
                        {
                            "path": [
                                35,
                                8,
                                10,
                                5,
                                2,
                                21
                            ],
                            "pathEdge": [
                                40,
                                42,
                                28,
                                15,
                                12
                            ],
                            "weight": 5.0027303958791425,
                            "reliability": 0.9972742551067019
                        }
                    ],
                    "HC": 5,
                    "OF": 0,
                    "CO": 2,
                    "WT": 0.13763806287170774
                },
                {
                    "redundantPathReliability": 0.99999657255249,
                    "redundantPath": [
                        {
                            "path": [
                                35,
                                8,
                                5,
                                2,
                                21
                            ],
                            "pathEdge": [
                                40,
                                26,
                                15,
                                12
                            ],
                            "weight": 4.002315165420757,
                            "reliability": 0.997688356123173
                        },
                        {
                            "path": [
                                35,
                                8,
                                9,
                                5,
                                2,
                                21
                            ],
                            "pathEdge": [
                                40,
                                41,
                                27,
                                15,
                                12
                            ],
                            "weight": 5.002970827141882,
                            "reliability": 0.9970346233014884
                        }
                    ],
                    "HC": 5,
                    "OF": 0,
                    "CO": 2,
                    "WT": 0.13763806287170774
                },
                {
                    "redundantPathReliability": 0.9999966903110554,
                    "redundantPath": [
                        {
                            "path": [
                                35,
                                8,
                                10,
                                4,
                                2,
                                21
                            ],
                            "pathEdge": [
                                40,
                                42,
                                23,
                                14,
                                12
                            ],
                            "weight": 5.002432273269067,
                            "reliability": 0.9975715343290366
                        },
                        {
                            "path": [
                                35,
                                8,
                                10,
                                5,
                                2,
                                21
                            ],
                            "pathEdge": [
                                40,
                                42,
                                28,
                                15,
                                12
                            ],
                            "weight": 5.0027303958791425,
                            "reliability": 0.9972742551067019
                        }
                    ],
                    "HC": 5,
                    "OF": 0,
                    "CO": 2,
                    "WT": 0.13763806287170774
                }
            ],
            "pathIndex": 0
        },
        {
            "start": 40,
            "end": 32,
            "ddl": 1000,
            "duration": 1,
            "period": 200,
            "reliability": 0.9998016538304698,
            "redundantPath": [
                {
                    "redundantPathReliability": 0.9999960494759755,
                    "redundantPath": [
                        {
                            "path": [
                                40,
                                11,
                                7,
                                32
                            ],
                            "pathEdge": [
                                49,
                                37,
                                35
                            ],
                            "weight": 3.0018764822618564,
                            "reliability": 0.9981259208771985
                        },
                        {
                            "path": [
                                40,
                                11,
                                6,
                                4,
                                0,
                                5,
                                10,
                                7,
                                32
                            ],
                            "pathEdge": [
                                49,
                                32,
                                21,
                                3,
                                4,
                                28,
                                36,
                                35
                            ],
                            "weight": 8.004226330973692,
                            "reliability": 0.9957840416086782
                        }
                    ],
                    "HC": 8,
                    "OF": 0,
                    "CO": 2,
                    "WT": 0.1656754460492778
                },
                {
                    "redundantPathReliability": 0.9999966227032024,
                    "redundantPath": [
                        {
                            "path": [
                                40,
                                11,
                                7,
                                32
                            ],
                            "pathEdge": [
                                49,
                                37,
                                35
                            ],
                            "weight": 3.0018764822618564,
                            "reliability": 0.9981259208771985
                        },
                        {
                            "path": [
                                40,
                                11,
                                6,
                                4,
                                10,
                                7,
                                32
                            ],
                            "pathEdge": [
                                49,
                                32,
                                21,
                                23,
                                36,
                                35
                            ],
                            "weight": 6.00361203985753,
                            "reliability": 0.9963957844280422
                        }
                    ],
                    "HC": 6,
                    "OF": 0,
                    "CO": 2,
                    "WT": 0.1469838572642311
                },
                {
                    "redundantPathReliability": 0.9999967419599516,
                    "redundantPath": [
                        {
                            "path": [
                                40,
                                11,
                                7,
                                32
                            ],
                            "pathEdge": [
                                49,
                                37,
                                35
                            ],
                            "weight": 3.0018764822618564,
                            "reliability": 0.9981259208771985
                        },
                        {
                            "path": [
                                40,
                                11,
                                6,
                                4,
                                7,
                                32
                            ],
                            "pathEdge": [
                                49,
                                32,
                                21,
                                22,
                                35
                            ],
                            "weight": 5.0034843323113085,
                            "reliability": 0.996523054133937
                        }
                    ],
                    "HC": 5,
                    "OF": 0,
                    "CO": 2,
                    "WT": 0.13763806287170774
                },
                {
                    "redundantPathReliability": 0.999996312853523,
                    "redundantPath": [
                        {
                            "path": [
                                40,
                                11,
                                6,
                                7,
                                32
                            ],
                            "pathEdge": [
                                49,
                                32,
                                31,
                                35
                            ],
                            "weight": 4.002123919199869,
                            "reliability": 0.9978790889364244
                        },
                        {
                            "path": [
                                40,
                                11,
                                6,
                                4,
                                7,
                                32
                            ],
                            "pathEdge": [
                                49,
                                32,
                                21,
                                22,
                                35
                            ],
                            "weight": 5.0034843323113085,
                            "reliability": 0.996523054133937
                        }
                    ],
                    "HC": 5,
                    "OF": 0,
                    "CO": 2,
                    "WT": 0.13763806287170774
                },
                {
                    "redundantPathReliability": 0.999998012618208,
                    "redundantPath": [
                        {
                            "path": [
                                40,
                                11,
                                7,
                                32
                            ],
                            "pathEdge": [
                                49,
                                37,
                                35
                            ],
                            "weight": 3.0018764822618564,
                            "reliability": 0.9981259208771985
                        },
                        {
                            "path": [
                                40,
                                11,
                                6,
                                7,
                                32
                            ],
                            "pathEdge": [
                                49,
                                32,
                                31,
                                35
                            ],
                            "weight": 4.002123919199869,
                            "reliability": 0.9978790889364244
                        }
                    ],
                    "HC": 4,
                    "OF": 0,
                    "CO": 2,
                    "WT": 0.12829226847918437
                }
            ],
            "pathIndex": 0
        },
        {
            "start": 42,
            "end": 20,
            "ddl": 1000,
            "duration": 1,
            "period": 100,
            "reliability": 0.9992481013044383,
            "redundantPath": [
                {
                    "redundantPathReliability": 0.9999989488023948,
                    "redundantPath": [
                        {
                            "path": [
                                42,
                                12,
                                8,
                                5,
                                2,
                                20
                            ],
                            "pathEdge": [
                                51,
                                43,
                                26,
                                15,
                                11
                            ],
                            "weight": 5.001393881425573,
                            "reliability": 0.9986073226135719
                        },
                        {
                            "path": [
                                42,
                                12,
                                8,
                                10,
                                4,
                                2,
                                20
                            ],
                            "pathEdge": [
                                51,
                                43,
                                42,
                                23,
                                14,
                                11
                            ],
                            "weight": 6.001510989273882,
                            "reliability": 0.9984903932153791
                        }
                    ],
                    "HC": 6,
                    "OF": 0,
                    "CO": 2,
                    "WT": 0.1469838572642311
                },
                {
                    "redundantPathReliability": 0.9999987416046862,
                    "redundantPath": [
                        {
                            "path": [
                                42,
                                12,
                                8,
                                5,
                                2,
                                20
                            ],
                            "pathEdge": [
                                51,
                                43,
                                26,
                                15,
                                11
                            ],
                            "weight": 5.001393881425573,
                            "reliability": 0.9986073226135719
                        },
                        {
                            "path": [
                                42,
                                12,
                                8,
                                10,
                                5,
                                2,
                                20
                            ],
                            "pathEdge": [
                                51,
                                43,
                                42,
                                28,
                                15,
                                11
                            ],
                            "weight": 6.001809111883958,
                            "reliability": 0.9981928401704205
                        }
                    ],
                    "HC": 6,
                    "OF": 0,
                    "CO": 2,
                    "WT": 0.1469838572642311
                },
                {
                    "redundantPathReliability": 0.9999985745860895,
                    "redundantPath": [
                        {
                            "path": [
                                42,
                                12,
                                8,
                                5,
                                2,
                                20
                            ],
                            "pathEdge": [
                                51,
                                43,
                                26,
                                15,
                                11
                            ],
                            "weight": 5.001393881425573,
                            "reliability": 0.9986073226135719
                        },
                        {
                            "path": [
                                42,
                                12,
                                8,
                                9,
                                5,
                                2,
                                20
                            ],
                            "pathEdge": [
                                51,
                                43,
                                41,
                                27,
                                15,
                                11
                            ],
                            "weight": 6.002049543146697,
                            "reliability": 0.9979529876413731
                        }
                    ],
                    "HC": 6,
                    "OF": 0,
                    "CO": 2,
                    "WT": 0.1469838572642311
                },
                {
                    "redundantPathReliability": 0.9999985668454823,
                    "redundantPath": [
                        {
                            "path": [
                                42,
                                12,
                                8,
                                5,
                                2,
                                20
                            ],
                            "pathEdge": [
                                51,
                                43,
                                26,
                                15,
                                11
                            ],
                            "weight": 5.001393881425573,
                            "reliability": 0.9986073226135719
                        },
                        {
                            "path": [
                                42,
                                12,
                                9,
                                5,
                                2,
                                20
                            ],
                            "pathEdge": [
                                51,
                                46,
                                27,
                                15,
                                11
                            ],
                            "weight": 5.002060753990611,
                            "reliability": 0.9979418714879474
                        }
                    ],
                    "HC": 5,
                    "OF": 0,
                    "CO": 2,
                    "WT": 0.13763806287170774
                },
                {
                    "redundantPathReliability": 0.9993036613067857,
                    "redundantPath": [
                        {
                            "path": [
                                42,
                                12,
                                8,
                                5,
                                2,
                                20
                            ],
                            "pathEdge": [
                                51,
                                43,
                                26,
                                15,
                                11
                            ],
                            "weight": 5.001393881425573,
                            "reliability": 0.9986073226135719
                        }
                    ],
                    "HC": 5,
                    "OF": 0,
                    "CO": 1,
                    "WT": 0.09218351741716227
                }
            ],
            "pathIndex": 0
        },
        {
            "start": 20,
            "end": 35,
            "ddl": 1000,
            "duration": 1,
            "period": 200,
            "reliability": 0.9998102699066456,
            "redundantPath": [
                {
                    "redundantPathReliability": 0.999998494945589,
                    "redundantPath": [
                        {
                            "path": [
                                20,
                                2,
                                5,
                                8,
                                35
                            ],
                            "pathEdge": [
                                11,
                                15,
                                26,
                                40
                            ],
                            "weight": 4.001817670966513,
                            "reliability": 0.9981846026946363
                        },
                        {
                            "path": [
                                20,
                                2,
                                4,
                                7,
                                10,
                                8,
                                35
                            ],
                            "pathEdge": [
                                11,
                                14,
                                22,
                                36,
                                42,
                                40
                            ],
                            "weight": 6.001659846228067,
                            "reliability": 0.9983419008485261
                        }
                    ],
                    "HC": 6,
                    "OF": 0,
                    "CO": 2,
                    "WT": 0.1469838572642311
                },
                {
                    "redundantPathReliability": 0.9999990030788101,
                    "redundantPath": [
                        {
                            "path": [
                                20,
                                2,
                                5,
                                8,
                                35
                            ],
                            "pathEdge": [
                                11,
                                15,
                                26,
                                40
                            ],
                            "weight": 4.001817670966513,
                            "reliability": 0.9981846026946363
                        },
                        {
                            "path": [
                                20,
                                2,
                                5,
                                10,
                                8,
                                35
                            ],
                            "pathEdge": [
                                11,
                                15,
                                28,
                                42,
                                40
                            ],
                            "weight": 5.001099116009623,
                            "reliability": 0.9989017046896052
                        }
                    ],
                    "HC": 5,
                    "OF": 0,
                    "CO": 2,
                    "WT": 0.13763806287170774
                },
                {
                    "redundantPathReliability": 0.9999987818876174,
                    "redundantPath": [
                        {
                            "path": [
                                20,
                                2,
                                5,
                                8,
                                35
                            ],
                            "pathEdge": [
                                11,
                                15,
                                26,
                                40
                            ],
                            "weight": 4.001817670966513,
                            "reliability": 0.9981846026946363
                        },
                        {
                            "path": [
                                20,
                                2,
                                4,
                                10,
                                8,
                                35
                            ],
                            "pathEdge": [
                                11,
                                14,
                                23,
                                42,
                                40
                            ],
                            "weight": 5.001343175265827,
                            "reliability": 0.998658021180453
                        }
                    ],
                    "HC": 5,
                    "OF": 0,
                    "CO": 2,
                    "WT": 0.13763806287170774
                },
                {
                    "redundantPathReliability": 0.9999980245860891,
                    "redundantPath": [
                        {
                            "path": [
                                20,
                                2,
                                5,
                                8,
                                35
                            ],
                            "pathEdge": [
                                11,
                                15,
                                26,
                                40
                            ],
                            "weight": 4.001817670966513,
                            "reliability": 0.9981846026946363
                        },
                        {
                            "path": [
                                20,
                                2,
                                5,
                                9,
                                8,
                                35
                            ],
                            "pathEdge": [
                                11,
                                15,
                                27,
                                41,
                                40
                            ],
                            "weight": 5.00217927315387,
                            "reliability": 0.9978237117697536
                        }
                    ],
                    "HC": 5,
                    "OF": 0,
                    "CO": 2,
                    "WT": 0.13763806287170774
                },
                {
                    "redundantPathReliability": 0.9999992630554846,
                    "redundantPath": [
                        {
                            "path": [
                                20,
                                2,
                                5,
                                10,
                                8,
                                35
                            ],
                            "pathEdge": [
                                11,
                                15,
                                28,
                                42,
                                40
                            ],
                            "weight": 5.001099116009623,
                            "reliability": 0.9989017046896052
                        },
                        {
                            "path": [
                                20,
                                2,
                                4,
                                10,
                                8,
                                35
                            ],
                            "pathEdge": [
                                11,
                                14,
                                23,
                                42,
                                40
                            ],
                            "weight": 5.001343175265827,
                            "reliability": 0.998658021180453
                        }
                    ],
                    "HC": 5,
                    "OF": 0,
                    "CO": 2,
                    "WT": 0.13763806287170774
                }
            ],
            "pathIndex": 0
        },
        {
            "start": 14,
            "end": 15,
            "ddl": 1000,
            "duration": 1,
            "period": 200,
            "reliability": 0.9997697471871253,
            "redundantPath": [
                {
                    "redundantPathReliability": 0.9994183666755677,
                    "redundantPath": [
                        {
                            "path": [
                                14,
                                0,
                                15
                            ],
                            "pathEdge": [
                                1,
                                2
                            ],
                            "weight": 2.0005818900440455,
                            "reliability": 0.9994183666755677
                        }
                    ],
                    "HC": 2,
                    "OF": 0,
                    "CO": 1,
                    "WT": 0.06414613423959219
                }
            ],
            "pathIndex": 0
        }
    ],
    "connections": {
        "successRate": 1,
        "connections": [
            [
                [
                    {
                        "srcNode": 35.0,
                        "dstNode": 8.0,
                        "timeslot": {
                            "startTime": 1.0,
                            "duration": 1.0
                        }
                    },
                    {
                        "srcNode": 35.0,
                        "dstNode": 8.0,
                        "timeslot": {
                            "startTime": 301.0,
                            "duration": 1.0
                        }
                    },
                    {
                        "srcNode": 8.0,
                        "dstNode": 5.0,
                        "timeslot": {
                            "startTime": 2.0,
                            "duration": 1.0
                        }
                    },
                    {
                        "srcNode": 8.0,
                        "dstNode": 5.0,
                        "timeslot": {
                            "startTime": 302.0,
                            "duration": 1.0
                        }
                    },
                    {
                        "srcNode": 5.0,
                        "dstNode": 2.0,
                        "timeslot": {
                            "startTime": 3.0,
                            "duration": 1.0
                        }
                    },
                    {
                        "srcNode": 5.0,
                        "dstNode": 2.0,
                        "timeslot": {
                            "startTime": 303.0,
                            "duration": 1.0
                        }
                    },
                    {
                        "srcNode": 2.0,
                        "dstNode": 21.0,
                        "timeslot": {
                            "startTime": 4.0,
                            "duration": 1.0
                        }
                    },
                    {
                        "srcNode": 2.0,
                        "dstNode": 21.0,
                        "timeslot": {
                            "startTime": 304.0,
                            "duration": 1.0
                        }
                    }
                ],
                [
                    {
                        "srcNode": 35.0,
                        "dstNode": 8.0,
                        "timeslot": {
                            "startTime": 2.0,
                            "duration": 1.0
                        }
                    },
                    {
                        "srcNode": 35.0,
                        "dstNode": 8.0,
                        "timeslot": {
                            "startTime": 302.0,
                            "duration": 1.0
                        }
                    },
                    {
                        "srcNode": 8.0,
                        "dstNode": 5.0,
                        "timeslot": {
                            "startTime": 3.0,
                            "duration": 1.0
                        }
                    },
                    {
                        "srcNode": 8.0,
                        "dstNode": 5.0,
                        "timeslot": {
                            "startTime": 303.0,
                            "duration": 1.0
                        }
                    },
                    {
                        "srcNode": 5.0,
                        "dstNode": 10.0,
                        "timeslot": {
                            "startTime": 4.0,
                            "duration": 1.0
                        }
                    },
                    {
                        "srcNode": 5.0,
                        "dstNode": 10.0,
                        "timeslot": {
                            "startTime": 304.0,
                            "duration": 1.0
                        }
                    },
                    {
                        "srcNode": 10.0,
                        "dstNode": 4.0,
                        "timeslot": {
                            "startTime": 5.0,
                            "duration": 1.0
                        }
                    },
                    {
                        "srcNode": 10.0,
                        "dstNode": 4.0,
                        "timeslot": {
                            "startTime": 305.0,
                            "duration": 1.0
                        }
                    },
                    {
                        "srcNode": 4.0,
                        "dstNode": 2.0,
                        "timeslot": {
                            "startTime": 6.0,
                            "duration": 1.0
                        }
                    },
                    {
                        "srcNode": 4.0,
                        "dstNode": 2.0,
                        "timeslot": {
                            "startTime": 306.0,
                            "duration": 1.0
                        }
                    },
                    {
                        "srcNode": 2.0,
                        "dstNode": 21.0,
                        "timeslot": {
                            "startTime": 7.0,
                            "duration": 1.0
                        }
                    },
                    {
                        "srcNode": 2.0,
                        "dstNode": 21.0,
                        "timeslot": {
                            "startTime": 307.0,
                            "duration": 1.0
                        }
                    }
                ]
            ],
            [
                [
                    {
                        "srcNode": 40.0,
                        "dstNode": 11.0,
                        "timeslot": {
                            "startTime": 1.0,
                            "duration": 1.0
                        }
                    },
                    {
                        "srcNode": 40.0,
                        "dstNode": 11.0,
                        "timeslot": {
                            "startTime": 201.0,
                            "duration": 1.0
                        }
                    },
                    {
                        "srcNode": 40.0,
                        "dstNode": 11.0,
                        "timeslot": {
                            "startTime": 401.0,
                            "duration": 1.0
                        }
                    },
                    {
                        "srcNode": 11.0,
                        "dstNode": 7.0,
                        "timeslot": {
                            "startTime": 2.0,
                            "duration": 1.0
                        }
                    },
                    {
                        "srcNode": 11.0,
                        "dstNode": 7.0,
                        "timeslot": {
                            "startTime": 202.0,
                            "duration": 1.0
                        }
                    },
                    {
                        "srcNode": 11.0,
                        "dstNode": 7.0,
                        "timeslot": {
                            "startTime": 402.0,
                            "duration": 1.0
                        }
                    },
                    {
                        "srcNode": 7.0,
                        "dstNode": 32.0,
                        "timeslot": {
                            "startTime": 3.0,
                            "duration": 1.0
                        }
                    },
                    {
                        "srcNode": 7.0,
                        "dstNode": 32.0,
                        "timeslot": {
                            "startTime": 203.0,
                            "duration": 1.0
                        }
                    },
                    {
                        "srcNode": 7.0,
                        "dstNode": 32.0,
                        "timeslot": {
                            "startTime": 403.0,
                            "duration": 1.0
                        }
                    }
                ],
                [
                    {
                        "srcNode": 40.0,
                        "dstNode": 11.0,
                        "timeslot": {
                            "startTime": 2.0,
                            "duration": 1.0
                        }
                    },
                    {
                        "srcNode": 40.0,
                        "dstNode": 11.0,
                        "timeslot": {
                            "startTime": 202.0,
                            "duration": 1.0
                        }
                    },
                    {
                        "srcNode": 40.0,
                        "dstNode": 11.0,
                        "timeslot": {
                            "startTime": 402.0,
                            "duration": 1.0
                        }
                    },
                    {
                        "srcNode": 11.0,
                        "dstNode": 6.0,
                        "timeslot": {
                            "startTime": 3.0,
                            "duration": 1.0
                        }
                    },
                    {
                        "srcNode": 11.0,
                        "dstNode": 6.0,
                        "timeslot": {
                            "startTime": 203.0,
                            "duration": 1.0
                        }
                    },
                    {
                        "srcNode": 11.0,
                        "dstNode": 6.0,
                        "timeslot": {
                            "startTime": 403.0,
                            "duration": 1.0
                        }
                    },
                    {
                        "srcNode": 6.0,
                        "dstNode": 4.0,
                        "timeslot": {
                            "startTime": 4.0,
                            "duration": 1.0
                        }
                    },
                    {
                        "srcNode": 6.0,
                        "dstNode": 4.0,
                        "timeslot": {
                            "startTime": 204.0,
                            "duration": 1.0
                        }
                    },
                    {
                        "srcNode": 6.0,
                        "dstNode": 4.0,
                        "timeslot": {
                            "startTime": 404.0,
                            "duration": 1.0
                        }
                    },
                    {
                        "srcNode": 4.0,
                        "dstNode": 0.0,
                        "timeslot": {
                            "startTime": 5.0,
                            "duration": 1.0
                        }
                    },
                    {
                        "srcNode": 4.0,
                        "dstNode": 0.0,
                        "timeslot": {
                            "startTime": 205.0,
                            "duration": 1.0
                        }
                    },
                    {
                        "srcNode": 4.0,
                        "dstNode": 0.0,
                        "timeslot": {
                            "startTime": 405.0,
                            "duration": 1.0
                        }
                    },
                    {
                        "srcNode": 0.0,
                        "dstNode": 5.0,
                        "timeslot": {
                            "startTime": 6.0,
                            "duration": 1.0
                        }
                    },
                    {
                        "srcNode": 0.0,
                        "dstNode": 5.0,
                        "timeslot": {
                            "startTime": 206.0,
                            "duration": 1.0
                        }
                    },
                    {
                        "srcNode": 0.0,
                        "dstNode": 5.0,
                        "timeslot": {
                            "startTime": 406.0,
                            "duration": 1.0
                        }
                    },
                    {
                        "srcNode": 5.0,
                        "dstNode": 10.0,
                        "timeslot": {
                            "startTime": 7.0,
                            "duration": 1.0
                        }
                    },
                    {
                        "srcNode": 5.0,
                        "dstNode": 10.0,
                        "timeslot": {
                            "startTime": 207.0,
                            "duration": 1.0
                        }
                    },
                    {
                        "srcNode": 5.0,
                        "dstNode": 10.0,
                        "timeslot": {
                            "startTime": 407.0,
                            "duration": 1.0
                        }
                    },
                    {
                        "srcNode": 10.0,
                        "dstNode": 7.0,
                        "timeslot": {
                            "startTime": 8.0,
                            "duration": 1.0
                        }
                    },
                    {
                        "srcNode": 10.0,
                        "dstNode": 7.0,
                        "timeslot": {
                            "startTime": 208.0,
                            "duration": 1.0
                        }
                    },
                    {
                        "srcNode": 10.0,
                        "dstNode": 7.0,
                        "timeslot": {
                            "startTime": 408.0,
                            "duration": 1.0
                        }
                    },
                    {
                        "srcNode": 7.0,
                        "dstNode": 32.0,
                        "timeslot": {
                            "startTime": 9.0,
                            "duration": 1.0
                        }
                    },
                    {
                        "srcNode": 7.0,
                        "dstNode": 32.0,
                        "timeslot": {
                            "startTime": 209.0,
                            "duration": 1.0
                        }
                    },
                    {
                        "srcNode": 7.0,
                        "dstNode": 32.0,
                        "timeslot": {
                            "startTime": 409.0,
                            "duration": 1.0
                        }
                    }
                ]
            ],
            [
                [
                    {
                        "srcNode": 42.0,
                        "dstNode": 12.0,
                        "timeslot": {
                            "startTime": 1.0,
                            "duration": 1.0
                        }
                    },
                    {
                        "srcNode": 42.0,
                        "dstNode": 12.0,
                        "timeslot": {
                            "startTime": 101.0,
                            "duration": 1.0
                        }
                    },
                    {
                        "srcNode": 42.0,
                        "dstNode": 12.0,
                        "timeslot": {
                            "startTime": 201.0,
                            "duration": 1.0
                        }
                    },
                    {
                        "srcNode": 42.0,
                        "dstNode": 12.0,
                        "timeslot": {
                            "startTime": 301.0,
                            "duration": 1.0
                        }
                    },
                    {
                        "srcNode": 42.0,
                        "dstNode": 12.0,
                        "timeslot": {
                            "startTime": 401.0,
                            "duration": 1.0
                        }
                    },
                    {
                        "srcNode": 42.0,
                        "dstNode": 12.0,
                        "timeslot": {
                            "startTime": 501.0,
                            "duration": 1.0
                        }
                    },
                    {
                        "srcNode": 12.0,
                        "dstNode": 8.0,
                        "timeslot": {
                            "startTime": 2.0,
                            "duration": 1.0
                        }
                    },
                    {
                        "srcNode": 12.0,
                        "dstNode": 8.0,
                        "timeslot": {
                            "startTime": 102.0,
                            "duration": 1.0
                        }
                    },
                    {
                        "srcNode": 12.0,
                        "dstNode": 8.0,
                        "timeslot": {
                            "startTime": 202.0,
                            "duration": 1.0
                        }
                    },
                    {
                        "srcNode": 12.0,
                        "dstNode": 8.0,
                        "timeslot": {
                            "startTime": 302.0,
                            "duration": 1.0
                        }
                    },
                    {
                        "srcNode": 12.0,
                        "dstNode": 8.0,
                        "timeslot": {
                            "startTime": 402.0,
                            "duration": 1.0
                        }
                    },
                    {
                        "srcNode": 12.0,
                        "dstNode": 8.0,
                        "timeslot": {
                            "startTime": 502.0,
                            "duration": 1.0
                        }
                    },
                    {
                        "srcNode": 42.0,
                        "dstNode": 12.0,
                        "timeslot": {
                            "startTime": 2.0,
                            "duration": 1.0
                        }
                    },
                    {
                        "srcNode": 42.0,
                        "dstNode": 12.0,
                        "timeslot": {
                            "startTime": 102.0,
                            "duration": 1.0
                        }
                    },
                    {
                        "srcNode": 42.0,
                        "dstNode": 12.0,
                        "timeslot": {
                            "startTime": 202.0,
                            "duration": 1.0
                        }
                    },
                    {
                        "srcNode": 42.0,
                        "dstNode": 12.0,
                        "timeslot": {
                            "startTime": 302.0,
                            "duration": 1.0
                        }
                    },
                    {
                        "srcNode": 42.0,
                        "dstNode": 12.0,
                        "timeslot": {
                            "startTime": 402.0,
                            "duration": 1.0
                        }
                    },
                    {
                        "srcNode": 42.0,
                        "dstNode": 12.0,
                        "timeslot": {
                            "startTime": 502.0,
                            "duration": 1.0
                        }
                    },
                    {
                        "srcNode": 12.0,
                        "dstNode": 8.0,
                        "timeslot": {
                            "startTime": 3.0,
                            "duration": 1.0
                        }
                    },
                    {
                        "srcNode": 12.0,
                        "dstNode": 8.0,
                        "timeslot": {
                            "startTime": 103.0,
                            "duration": 1.0
                        }
                    },
                    {
                        "srcNode": 12.0,
                        "dstNode": 8.0,
                        "timeslot": {
                            "startTime": 203.0,
                            "duration": 1.0
                        }
                    },
                    {
                        "srcNode": 12.0,
                        "dstNode": 8.0,
                        "timeslot": {
                            "startTime": 303.0,
                            "duration": 1.0
                        }
                    },
                    {
                        "srcNode": 12.0,
                        "dstNode": 8.0,
                        "timeslot": {
                            "startTime": 403.0,
                            "duration": 1.0
                        }
                    },
                    {
                        "srcNode": 12.0,
                        "dstNode": 8.0,
                        "timeslot": {
                            "startTime": 503.0,
                            "duration": 1.0
                        }
                    },
                    {
                        "srcNode": 8.0,
                        "dstNode": 5.0,
                        "timeslot": {
                            "startTime": 4.0,
                            "duration": 1.0
                        }
                    },
                    {
                        "srcNode": 8.0,
                        "dstNode": 5.0,
                        "timeslot": {
                            "startTime": 104.0,
                            "duration": 1.0
                        }
                    },
                    {
                        "srcNode": 8.0,
                        "dstNode": 5.0,
                        "timeslot": {
                            "startTime": 204.0,
                            "duration": 1.0
                        }
                    },
                    {
                        "srcNode": 8.0,
                        "dstNode": 5.0,
                        "timeslot": {
                            "startTime": 304.0,
                            "duration": 1.0
                        }
                    },
                    {
                        "srcNode": 8.0,
                        "dstNode": 5.0,
                        "timeslot": {
                            "startTime": 404.0,
                            "duration": 1.0
                        }
                    },
                    {
                        "srcNode": 8.0,
                        "dstNode": 5.0,
                        "timeslot": {
                            "startTime": 504.0,
                            "duration": 1.0
                        }
                    },
                    {
                        "srcNode": 5.0,
                        "dstNode": 2.0,
                        "timeslot": {
                            "startTime": 5.0,
                            "duration": 1.0
                        }
                    },
                    {
                        "srcNode": 5.0,
                        "dstNode": 2.0,
                        "timeslot": {
                            "startTime": 105.0,
                            "duration": 1.0
                        }
                    },
                    {
                        "srcNode": 5.0,
                        "dstNode": 2.0,
                        "timeslot": {
                            "startTime": 205.0,
                            "duration": 1.0
                        }
                    },
                    {
                        "srcNode": 5.0,
                        "dstNode": 2.0,
                        "timeslot": {
                            "startTime": 305.0,
                            "duration": 1.0
                        }
                    },
                    {
                        "srcNode": 5.0,
                        "dstNode": 2.0,
                        "timeslot": {
                            "startTime": 405.0,
                            "duration": 1.0
                        }
                    },
                    {
                        "srcNode": 5.0,
                        "dstNode": 2.0,
                        "timeslot": {
                            "startTime": 505.0,
                            "duration": 1.0
                        }
                    },
                    {
                        "srcNode": 2.0,
                        "dstNode": 20.0,
                        "timeslot": {
                            "startTime": 6.0,
                            "duration": 1.0
                        }
                    },
                    {
                        "srcNode": 2.0,
                        "dstNode": 20.0,
                        "timeslot": {
                            "startTime": 106.0,
                            "duration": 1.0
                        }
                    },
                    {
                        "srcNode": 2.0,
                        "dstNode": 20.0,
                        "timeslot": {
                            "startTime": 206.0,
                            "duration": 1.0
                        }
                    },
                    {
                        "srcNode": 2.0,
                        "dstNode": 20.0,
                        "timeslot": {
                            "startTime": 306.0,
                            "duration": 1.0
                        }
                    },
                    {
                        "srcNode": 2.0,
                        "dstNode": 20.0,
                        "timeslot": {
                            "startTime": 406.0,
                            "duration": 1.0
                        }
                    },
                    {
                        "srcNode": 2.0,
                        "dstNode": 20.0,
                        "timeslot": {
                            "startTime": 506.0,
                            "duration": 1.0
                        }
                    }
                ],
                [
                    {
                        "srcNode": 42.0,
                        "dstNode": 12.0,
                        "timeslot": {
                            "startTime": 3.0,
                            "duration": 1.0
                        }
                    },
                    {
                        "srcNode": 42.0,
                        "dstNode": 12.0,
                        "timeslot": {
                            "startTime": 103.0,
                            "duration": 1.0
                        }
                    },
                    {
                        "srcNode": 42.0,
                        "dstNode": 12.0,
                        "timeslot": {
                            "startTime": 203.0,
                            "duration": 1.0
                        }
                    },
                    {
                        "srcNode": 42.0,
                        "dstNode": 12.0,
                        "timeslot": {
                            "startTime": 303.0,
                            "duration": 1.0
                        }
                    },
                    {
                        "srcNode": 42.0,
                        "dstNode": 12.0,
                        "timeslot": {
                            "startTime": 403.0,
                            "duration": 1.0
                        }
                    },
                    {
                        "srcNode": 42.0,
                        "dstNode": 12.0,
                        "timeslot": {
                            "startTime": 503.0,
                            "duration": 1.0
                        }
                    },
                    {
                        "srcNode": 12.0,
                        "dstNode": 8.0,
                        "timeslot": {
                            "startTime": 4.0,
                            "duration": 1.0
                        }
                    },
                    {
                        "srcNode": 12.0,
                        "dstNode": 8.0,
                        "timeslot": {
                            "startTime": 104.0,
                            "duration": 1.0
                        }
                    },
                    {
                        "srcNode": 12.0,
                        "dstNode": 8.0,
                        "timeslot": {
                            "startTime": 204.0,
                            "duration": 1.0
                        }
                    },
                    {
                        "srcNode": 12.0,
                        "dstNode": 8.0,
                        "timeslot": {
                            "startTime": 304.0,
                            "duration": 1.0
                        }
                    },
                    {
                        "srcNode": 12.0,
                        "dstNode": 8.0,
                        "timeslot": {
                            "startTime": 404.0,
                            "duration": 1.0
                        }
                    },
                    {
                        "srcNode": 12.0,
                        "dstNode": 8.0,
                        "timeslot": {
                            "startTime": 504.0,
                            "duration": 1.0
                        }
                    },
                    {
                        "srcNode": 8.0,
                        "dstNode": 10.0,
                        "timeslot": {
                            "startTime": 5.0,
                            "duration": 1.0
                        }
                    },
                    {
                        "srcNode": 8.0,
                        "dstNode": 10.0,
                        "timeslot": {
                            "startTime": 105.0,
                            "duration": 1.0
                        }
                    },
                    {
                        "srcNode": 8.0,
                        "dstNode": 10.0,
                        "timeslot": {
                            "startTime": 205.0,
                            "duration": 1.0
                        }
                    },
                    {
                        "srcNode": 8.0,
                        "dstNode": 10.0,
                        "timeslot": {
                            "startTime": 305.0,
                            "duration": 1.0
                        }
                    },
                    {
                        "srcNode": 8.0,
                        "dstNode": 10.0,
                        "timeslot": {
                            "startTime": 405.0,
                            "duration": 1.0
                        }
                    },
                    {
                        "srcNode": 8.0,
                        "dstNode": 10.0,
                        "timeslot": {
                            "startTime": 505.0,
                            "duration": 1.0
                        }
                    },
                    {
                        "srcNode": 10.0,
                        "dstNode": 4.0,
                        "timeslot": {
                            "startTime": 6.0,
                            "duration": 1.0
                        }
                    },
                    {
                        "srcNode": 10.0,
                        "dstNode": 4.0,
                        "timeslot": {
                            "startTime": 106.0,
                            "duration": 1.0
                        }
                    },
                    {
                        "srcNode": 10.0,
                        "dstNode": 4.0,
                        "timeslot": {
                            "startTime": 206.0,
                            "duration": 1.0
                        }
                    },
                    {
                        "srcNode": 10.0,
                        "dstNode": 4.0,
                        "timeslot": {
                            "startTime": 306.0,
                            "duration": 1.0
                        }
                    },
                    {
                        "srcNode": 10.0,
                        "dstNode": 4.0,
                        "timeslot": {
                            "startTime": 406.0,
                            "duration": 1.0
                        }
                    },
                    {
                        "srcNode": 10.0,
                        "dstNode": 4.0,
                        "timeslot": {
                            "startTime": 506.0,
                            "duration": 1.0
                        }
                    },
                    {
                        "srcNode": 4.0,
                        "dstNode": 2.0,
                        "timeslot": {
                            "startTime": 7.0,
                            "duration": 1.0
                        }
                    },
                    {
                        "srcNode": 4.0,
                        "dstNode": 2.0,
                        "timeslot": {
                            "startTime": 107.0,
                            "duration": 1.0
                        }
                    },
                    {
                        "srcNode": 4.0,
                        "dstNode": 2.0,
                        "timeslot": {
                            "startTime": 207.0,
                            "duration": 1.0
                        }
                    },
                    {
                        "srcNode": 4.0,
                        "dstNode": 2.0,
                        "timeslot": {
                            "startTime": 307.0,
                            "duration": 1.0
                        }
                    },
                    {
                        "srcNode": 4.0,
                        "dstNode": 2.0,
                        "timeslot": {
                            "startTime": 407.0,
                            "duration": 1.0
                        }
                    },
                    {
                        "srcNode": 4.0,
                        "dstNode": 2.0,
                        "timeslot": {
                            "startTime": 507.0,
                            "duration": 1.0
                        }
                    },
                    {
                        "srcNode": 2.0,
                        "dstNode": 20.0,
                        "timeslot": {
                            "startTime": 8.0,
                            "duration": 1.0
                        }
                    },
                    {
                        "srcNode": 2.0,
                        "dstNode": 20.0,
                        "timeslot": {
                            "startTime": 108.0,
                            "duration": 1.0
                        }
                    },
                    {
                        "srcNode": 2.0,
                        "dstNode": 20.0,
                        "timeslot": {
                            "startTime": 208.0,
                            "duration": 1.0
                        }
                    },
                    {
                        "srcNode": 2.0,
                        "dstNode": 20.0,
                        "timeslot": {
                            "startTime": 308.0,
                            "duration": 1.0
                        }
                    },
                    {
                        "srcNode": 2.0,
                        "dstNode": 20.0,
                        "timeslot": {
                            "startTime": 408.0,
                            "duration": 1.0
                        }
                    },
                    {
                        "srcNode": 2.0,
                        "dstNode": 20.0,
                        "timeslot": {
                            "startTime": 508.0,
                            "duration": 1.0
                        }
                    }
                ]
            ],
            [
                [
                    {
                        "srcNode": 20.0,
                        "dstNode": 2.0,
                        "timeslot": {
                            "startTime": 1.0,
                            "duration": 1.0
                        }
                    },
                    {
                        "srcNode": 20.0,
                        "dstNode": 2.0,
                        "timeslot": {
                            "startTime": 201.0,
                            "duration": 1.0
                        }
                    },
                    {
                        "srcNode": 20.0,
                        "dstNode": 2.0,
                        "timeslot": {
                            "startTime": 401.0,
                            "duration": 1.0
                        }
                    },
                    {
                        "srcNode": 2.0,
                        "dstNode": 5.0,
                        "timeslot": {
                            "startTime": 2.0,
                            "duration": 1.0
                        }
                    },
                    {
                        "srcNode": 2.0,
                        "dstNode": 5.0,
                        "timeslot": {
                            "startTime": 202.0,
                            "duration": 1.0
                        }
                    },
                    {
                        "srcNode": 2.0,
                        "dstNode": 5.0,
                        "timeslot": {
                            "startTime": 402.0,
                            "duration": 1.0
                        }
                    },
                    {
                        "srcNode": 5.0,
                        "dstNode": 8.0,
                        "timeslot": {
                            "startTime": 3.0,
                            "duration": 1.0
                        }
                    },
                    {
                        "srcNode": 5.0,
                        "dstNode": 8.0,
                        "timeslot": {
                            "startTime": 203.0,
                            "duration": 1.0
                        }
                    },
                    {
                        "srcNode": 5.0,
                        "dstNode": 8.0,
                        "timeslot": {
                            "startTime": 403.0,
                            "duration": 1.0
                        }
                    },
                    {
                        "srcNode": 8.0,
                        "dstNode": 35.0,
                        "timeslot": {
                            "startTime": 4.0,
                            "duration": 1.0
                        }
                    },
                    {
                        "srcNode": 8.0,
                        "dstNode": 35.0,
                        "timeslot": {
                            "startTime": 204.0,
                            "duration": 1.0
                        }
                    },
                    {
                        "srcNode": 8.0,
                        "dstNode": 35.0,
                        "timeslot": {
                            "startTime": 404.0,
                            "duration": 1.0
                        }
                    }
                ],
                [
                    {
                        "srcNode": 20.0,
                        "dstNode": 2.0,
                        "timeslot": {
                            "startTime": 2.0,
                            "duration": 1.0
                        }
                    },
                    {
                        "srcNode": 20.0,
                        "dstNode": 2.0,
                        "timeslot": {
                            "startTime": 202.0,
                            "duration": 1.0
                        }
                    },
                    {
                        "srcNode": 20.0,
                        "dstNode": 2.0,
                        "timeslot": {
                            "startTime": 402.0,
                            "duration": 1.0
                        }
                    },
                    {
                        "srcNode": 2.0,
                        "dstNode": 4.0,
                        "timeslot": {
                            "startTime": 3.0,
                            "duration": 1.0
                        }
                    },
                    {
                        "srcNode": 2.0,
                        "dstNode": 4.0,
                        "timeslot": {
                            "startTime": 203.0,
                            "duration": 1.0
                        }
                    },
                    {
                        "srcNode": 2.0,
                        "dstNode": 4.0,
                        "timeslot": {
                            "startTime": 403.0,
                            "duration": 1.0
                        }
                    },
                    {
                        "srcNode": 4.0,
                        "dstNode": 7.0,
                        "timeslot": {
                            "startTime": 4.0,
                            "duration": 1.0
                        }
                    },
                    {
                        "srcNode": 4.0,
                        "dstNode": 7.0,
                        "timeslot": {
                            "startTime": 204.0,
                            "duration": 1.0
                        }
                    },
                    {
                        "srcNode": 4.0,
                        "dstNode": 7.0,
                        "timeslot": {
                            "startTime": 404.0,
                            "duration": 1.0
                        }
                    },
                    {
                        "srcNode": 7.0,
                        "dstNode": 10.0,
                        "timeslot": {
                            "startTime": 5.0,
                            "duration": 1.0
                        }
                    },
                    {
                        "srcNode": 7.0,
                        "dstNode": 10.0,
                        "timeslot": {
                            "startTime": 205.0,
                            "duration": 1.0
                        }
                    },
                    {
                        "srcNode": 7.0,
                        "dstNode": 10.0,
                        "timeslot": {
                            "startTime": 405.0,
                            "duration": 1.0
                        }
                    },
                    {
                        "srcNode": 10.0,
                        "dstNode": 8.0,
                        "timeslot": {
                            "startTime": 6.0,
                            "duration": 1.0
                        }
                    },
                    {
                        "srcNode": 10.0,
                        "dstNode": 8.0,
                        "timeslot": {
                            "startTime": 206.0,
                            "duration": 1.0
                        }
                    },
                    {
                        "srcNode": 10.0,
                        "dstNode": 8.0,
                        "timeslot": {
                            "startTime": 406.0,
                            "duration": 1.0
                        }
                    },
                    {
                        "srcNode": 8.0,
                        "dstNode": 35.0,
                        "timeslot": {
                            "startTime": 7.0,
                            "duration": 1.0
                        }
                    },
                    {
                        "srcNode": 8.0,
                        "dstNode": 35.0,
                        "timeslot": {
                            "startTime": 207.0,
                            "duration": 1.0
                        }
                    },
                    {
                        "srcNode": 8.0,
                        "dstNode": 35.0,
                        "timeslot": {
                            "startTime": 407.0,
                            "duration": 1.0
                        }
                    }
                ]
            ],
            [
                [
                    {
                        "srcNode": 14,
                        "dstNode": 0,
                        "timeslot": {
                            "startTime": 1,
                            "duration": 1
                        }
                    },
                    {
                        "srcNode": 14,
                        "dstNode": 0,
                        "timeslot": {
                            "startTime": 201,
                            "duration": 1
                        }
                    },
                    {
                        "srcNode": 14,
                        "dstNode": 0,
                        "timeslot": {
                            "startTime": 401,
                            "duration": 1
                        }
                    },
                    {
                        "srcNode": 0,
                        "dstNode": 15,
                        "timeslot": {
                            "startTime": 2,
                            "duration": 1
                        }
                    },
                    {
                        "srcNode": 0,
                        "dstNode": 15,
                        "timeslot": {
                            "startTime": 202,
                            "duration": 1
                        }
                    },
                    {
                        "srcNode": 0,
                        "dstNode": 15,
                        "timeslot": {
                            "startTime": 402,
                            "duration": 1
                        }
                    }
                ]
            ]
        ]
    }
}